Workbook

Sheet README
A1: Mock SSM Capital & RWA Model
A3: What this is:
A4: A small exercise I built to actually understand how RWA and CET1
A5: ratios work, using a mock portfolio shaped like State Street Markets'
A6: real business (repo, securities lending, derivatives). Built this
A7: mainly to prep for a Capital Optimization Analyst role - reading about
A8: Basel III wasn't clicking until I tried building the math myself.
A10: Update: adding a Basel III Endgame comparison.
A11: Regulators put out a re-proposed Basel III Endgame rule in March 2026
A12: that's expected to ease up capital requirements a bit compared to the
A13: 2023 version (still not final as of this workbook). Since this directly
A14: affects the kind of work this role does, I'm adding a side-by-side:
... A28: - the Basel III Endgame risk-weight adjustment (illustrative only)
A30: Sources I pulled from: | B30: Link
A31: State Street 10-Q, June 30 2026 (RWA Roll-Forward table, Note 9 on Indemnified Securities Financing, repo/sec-lending maturity table) | B31: https://www.sec.gov/Archives/edgar/data/0000093751/000009375126000397/stt-20260630.htm
A32: State Street 2025 Dodd-Frank Act Stress Test Disclosure, July 1 2025 (Severely Adverse scenario assumptions) | B32: https://s203.q4cdn.com/888565246/files/doc_downloads/Dodd_Frank/2025/2025-Federal-Reserve-Stress-Test-Disclosure-vfinal.pdf
A33: State Street 2Q26 Earnings Release Addendum (real CET1, RWA used to sanity-check the model) | B33: https://s203.q4cdn.com/888565246/files/doc_financials/2026/q2/STT-2Q26-Earnings-Release-Addendum-vFinal.pdf
A34: Federal Reserve press release, March 19 2026, on the Basel III Endgame re-proposal (used for direction/magnitude only, not exact figures) | B34: https://www.federalreserve.gov/newsevents/pressreleases/bcreg20260319a.htm
A36: What's in each sheet:
A37: 1. Portfolio - the mock transactions, with live RWA formulas
A38: 2. Capital_Summary - baseline CET1 ratio + check against the real number
A39: 3. Stress_Scenario - Severely Adverse shocks applied, stressed CET1 ratio
A40: 4. Basel_III_Endgame - current rules vs. the proposed rules, side by side

Sheet Portfolio
A1: ID | B1: Category | C1: Counterparty (mock) | D1: Exposure ($M) | E1: Collateral ($M) | F1: Haircut (%) | G1: Risk Weight (%) | H1: E* = Exposure net of collateral ($M) | I1: RWA ($M) | J1: Collateral is equity-type? (Y/N)
A2: Repo-01 | B2: Repo-style transactions | C2: ABC Broker-Dealer | D2: 420 | E2: 435 | F2: 0.02 | G2: 0.2 | H2: =MAX(0,D2-E2*(1-F2)) -> 0 | I2: =H2*G2 -> 0 | J2: N
A3: Repo-02 | B3: Repo-style transactions | C3: DEF Broker-Dealer | D3: 310 | E3: 318 | F3: 0.02 | G3: 0.2 | H3: =MAX(0,D3-E3*(1-F3)) -> 0 | I3: =H3*G3 -> 0 | J3: N
A4: Repo-03 | B4: Repo-style transactions | C4: GHI Sponsored Repo Client (FICC) | D4: 260 | E4: 268 | F4: 0.02 | G4: 0.2 | H4: =MAX(0,D4-E4*(1-F4)) -> 0 | I4: =H4*G4 -> 0 | J4: N
A5: Repo-04 | B5: Repo-style transactions | C5: JKL Sponsored Repo Client (FICC) | D5: 180 | E5: 185 | F5: 0.02 | G5: 0.2 | H5: =MAX(0,D5-E5*(1-F5)) -> 0 | I5: =H5*G5 -> 0 | J5: N
A6: Deriv-01 | B6: OTC derivatives | C6: MNO Asset Manager - FX fwd | D6: 150 | E6: 90 | F6: 0.05 | G6: 0.5 | H6: =MAX(0,D6-E6*(1-F6)) -> 64.5 | I6: =H6*G6 -> 32.25 | J6: N
A7: Deriv-02 | B7: OTC derivatives | C7: PQR Asset Manager - FX swap | D7: 130 | E7: 70 | F7: 0.05 | G7: 0.5 | H7: =MAX(0,D7-E7*(1-F7)) -> 63.5 | I7: =H7*G7 -> 31.75 | J7: N
A8: Deriv-03 | B8: OTC derivatives | C8: STU Pension Fund - IR swap | D8: 95 | E8: 40 | F8: 0.05 | G8: 0.5 | H8: =MAX(0,D8-E8*(1-F8)) -> 57 | I8: =H8*G8 -> 28.5 | J8: N
A9: Deriv-04 | B9: OTC derivatives | C9: VWX Sovereign Fund - FX fwd | D9: 80 | E9: 45 | F9: 0.05 | G9: 0.2 | H9: =MAX(0,D9-E9*(1-F9)) -> 37.25 | I9: =H9*G9 -> 7.45 | J9: N
A10: Loan-01 | B10: Loans | C10: YZA Corp | D10: 60 | E10: 20 | F10: 0.1 | G10: 1 | H10: =MAX(0,D10-E10*(1-F10)) -> 42 | I10: =H10*G10 -> 42 | J10: N
A11: Loan-02 | B11: Loans | C11: BCD Corp | D11: 45 | E11: 15 | F11: 0.1 | G11: 1 | H11: =MAX(0,D11-E11*(1-F11)) -> 31.5 | I11: =H11*G11 -> 31.5 | J11: N
A12: Loan-03 | B12: Loans | C12: EFG Real Estate LLC | D12: 35 | E12: 10 | F12: 0.1 | G12: 1 | H12: =MAX(0,D12-E12*(1-F12)) -> 26 | I12: =H12*G12 -> 26 | J12: N
A13: Sec-01 | B13: Securitization | C13: HIJ ABS Tranche | D13: 25 | E13: 5 | F13: 0.03 | G13: 0.75 | H13: =MAX(0,D13-E13*(1-F13)) -> 20.15 | I13: =H13*G13 -> 15.1125 | J13: Y
... A17: Indem-03 | B17: Indemnified securities financing | C17: TUV Hedge Fund (borrower) | D17: 150 | E17: 158 | F17: 0.02 | G17: 0.2 | H17: =MAX(0,D17-E17*(1-F17)) -> 0 | I17: =H17*G17 -> 0 | J17: Y
C19: TOTAL PORTFOLIO | D19: =SUM(D2:D17) -> 2480 | E19: =SUM(E2:E17) -> 2209 | H19: =SUM(H2:H17) -> 358.02 | I19: =SUM(I2:I17) -> 226.6525
B22: RWA by category | J22: % of total RWA
B23: Indemnified securities financing | I23: =SUMIF(B2:B17,B23,I2:I17) -> 0 | J23: =I23/$I$19 -> 0
B24: Loans | I24: =SUMIF(B2:B17,B24,I2:I17) -> 99.5 | J24: =I24/$I$19 -> 0.43899803
B25: OTC derivatives | I25: =SUMIF(B2:B17,B25,I2:I17) -> 99.95 | J25: =I25/$I$19 -> 0.44098344
B26: Repo-style transactions | I26: =SUMIF(B2:B17,B26,I2:I17) -> 0 | J26: =I26/$I$19 -> 0
B27: Securitization | I27: =SUMIF(B2:B17,B27,I2:I17) -> 27.2025 | J27: =I27/$I$19 -> 0.12001853

Sheet Capital_Summary
A1: Capital Summary - Baseline (no stress)
A3: Total RWA ($M) | B3: =Portfolio!I19 -> 226.6525 | C3: Sum of mock portfolio RWA (Portfolio sheet)
A4: CET1 Capital ($M) - assumption | B4: 24.5 | C4: Set so baseline CET1 ratio lands near State Street's real 2Q26 ratio (~10.8%) for calibration
A5: CET1 Ratio | B5: =B4/B3 -> 0.10809499 | C5: CET1 Ratio = CET1 Capital / Total RWA
A7: Calibration check
A8: Real State Street CET1 Ratio, 2Q26 (Standardized) | B8: 0.108 | C8: Source: State Street 2Q26 Earnings Release Addendum, Regulatory Capital table
A9: Difference (mock model vs real) | B9: =B5-B8 -> 9.4991231e-05 | C9: Directional check only - mock model is a different scale/book
A11: RWA composition check vs real 10-Q roll-forward
A12: Real: Credit risk RWA, % of total (2Q26 Standardized) | B12: 0.981 | C12: $140,668M credit / $143,406M total. Source: 10-Q Table, June 30 2026
A13: Mock model: RWA in credit-risk-style categories, % of total | B13: =(Portfolio!I24+Portfolio!I25+Portfolio!I26+Portfolio!I27+Portfolio!I23)/Portfolio!I19 -> 1 | C13: All mock categories are credit-risk-style, so this should read ~100%

Sheet Stress_Scenario
A1: Stress Scenario - Supervisory Severely Adverse
A2: Source: State Street 2025 DFAST Disclosure (Severely Adverse scenario: unemployment 10%, real GDP -7.8%, equity market -50%). Row-level shocks below are my own simplified way of applying those macro assumptions to this mock portfolio - not State Street's actual stress methodology.
A4: Stress assumptions
A5: Equity market shock (Severely Adverse) | B5: -0.5 | C5: DFAST 2025: equity market decline of 50% over the 9-quarter horizon
A6: Haircut add-on under stress | B6: 0.05 | C6: Illustrative: wider haircuts as market liquidity deteriorates
A7: Risk weight add-on under stress | B7: 0.1 | C7: Illustrative: credit migration as unemployment rises to 10%, GDP falls 7.8%
A9: ID | B9: Category | C9: Counterparty (mock) | D9: Exposure ($M) | E9: Stressed Collateral ($M) | F9: Stressed Haircut (%) | G9: Stressed Risk Weight (%) | H9: Stressed E* ($M) | I9: Stressed RWA ($M)
A10: =Portfolio!A2 -> Repo-01 | B10: =Portfolio!B2 -> Repo-style transactions | C10: =Portfolio!C2 -> ABC Broker-Dealer | D10: =Portfolio!D2 -> 420 | E10: =IF(Portfolio!J2="Y",Portfolio!E2*(1+$B$5),Portfolio!E2) -> 435 | F10: =Portfolio!F2+$B$6 -> 0.07 | G10: =MIN(1,Portfolio!G2+$B$7) -> 0.3 | H10: =MAX(0,D10-E10*(1-F10)) -> 15.45 | I10: =H10*G10 -> 4.635
A11: =Portfolio!A3 -> Repo-02 | B11: =Portfolio!B3 -> Repo-style transactions | C11: =Portfolio!C3 -> DEF Broker-Dealer | D11: =Portfolio!D3 -> 310 | E11: =IF(Portfolio!J3="Y",Portfolio!E3*(1+$B$5),Portfolio!E3) -> 318 | F11: =Portfolio!F3+$B$6 -> 0.07 | G11: =MIN(1,Portfolio!G3+$B$7) -> 0.3 | H11: =MAX(0,D11-E11*(1-F11)) -> 14.26 | I11: =H11*G11 -> 4.278
A12: =Portfolio!A4 -> Repo-03 | B12: =Portfolio!B4 -> Repo-style transactions | C12: =Portfolio!C4 -> GHI Sponsored Repo Client (FICC) | D12: =Portfolio!D4 -> 260 | E12: =IF(Portfolio!J4="Y",Portfolio!E4*(1+$B$5),Portfolio!E4) -> 268 | F12: =Portfolio!F4+$B$6 -> 0.07 | G12: =MIN(1,Portfolio!G4+$B$7) -> 0.3 | H12: =MAX(0,D12-E12*(1-F12)) -> 10.76 | I12: =H12*G12 -> 3.228
A13: =Portfolio!A5 -> Repo-04 | B13: =Portfolio!B5 -> Repo-style transactions | C13: =Portfolio!C5 -> JKL Sponsored Repo Client (FICC) | D13: =Portfolio!D5 -> 180 | E13: =IF(Portfolio!J5="Y",Portfolio!E5*(1+$B$5),Portfolio!E5) -> 185 | F13: =Portfolio!F5+$B$6 -> 0.07 | G13: =MIN(1,Portfolio!G5+$B$7) -> 0.3 | H13: =MAX(0,D13-E13*(1-F13)) -> 7.95 | I13: =H13*G13 -> 2.385
A14: =Portfolio!A6 -> Deriv-01 | B14: =Portfolio!B6 -> OTC derivatives | C14: =Portfolio!C6 -> MNO Asset Manager - FX fwd | D14: =Portfolio!D6 -> 150 | E14: =IF(Portfolio!J6="Y",Portfolio!E6*(1+$B$5),Portfolio!E6) -> 90 | F14: =Portfolio!F6+$B$6 -> 0.1 | G14: =MIN(1,Portfolio!G6+$B$7) -> 0.6 | H14: =MAX(0,D14-E14*(1-F14)) -> 69 | I14: =H14*G14 -> 41.4
A15: =Portfolio!A7 -> Deriv-02 | B15: =Portfolio!B7 -> OTC derivatives | C15: =Portfolio!C7 -> PQR Asset Manager - FX swap | D15: =Portfolio!D7 -> 130 | E15: =IF(Portfolio!J7="Y",Portfolio!E7*(1+$B$5),Portfolio!E7) -> 70 | F15: =Portfolio!F7+$B$6 -> 0.1 | G15: =MIN(1,Portfolio!G7+$B$7) -> 0.6 | H15: =MAX(0,D15-E15*(1-F15)) -> 67 | I15: =H15*G15 -> 40.2
A16: =Portfolio!A8 -> Deriv-03 | B16: =Portfolio!B8 -> OTC derivatives | C16: =Portfolio!C8 -> STU Pension Fund - IR swap | D16: =Portfolio!D8 -> 95 | E16: =IF(Portfolio!J8="Y",Portfolio!E8*(1+$B$5),Portfolio!E8) -> 40 | F16: =Portfolio!F8+$B$6 -> 0.1 | G16: =MIN(1,Portfolio!G8+$B$7) -> 0.6 | H16: =MAX(0,D16-E16*(1-F16)) -> 59 | I16: =H16*G16 -> 35.4
A17: =Portfolio!A9 -> Deriv-04 | B17: =Portfolio!B9 -> OTC derivatives | C17: =Portfolio!C9 -> VWX Sovereign Fund - FX fwd | D17: =Portfolio!D9 -> 80 | E17: =IF(Portfolio!J9="Y",Portfolio!E9*(1+$B$5),Portfolio!E9) -> 45 | F17: =Portfolio!F9+$B$6 -> 0.1 | G17: =MIN(1,Portfolio!G9+$B$7) -> 0.3 | H17: =MAX(0,D17-E17*(1-F17)) -> 39.5 | I17: =H17*G17 -> 11.85
A18: =Portfolio!A10 -> Loan-01 | B18: =Portfolio!B10 -> Loans | C18: =Portfolio!C10 -> YZA Corp | D18: =Portfolio!D10 -> 60 | E18: =IF(Portfolio!J10="Y",Portfolio!E10*(1+$B$5),Portfolio!E10) -> 20 | F18: =Portfolio!F10+$B$6 -> 0.15 | G18: =MIN(1,Portfolio!G10+$B$7) -> 1 | H18: =MAX(0,D18-E18*(1-F18)) -> 43 | I18: =H18*G18 -> 43
A19: =Portfolio!A11 -> Loan-02 | B19: =Portfolio!B11 -> Loans | C19: =Portfolio!C11 -> BCD Corp | D19: =Portfolio!D11 -> 45 | E19: =IF(Portfolio!J11="Y",Portfolio!E11*(1+$B$5),Portfolio!E11) -> 15 | F19: =Portfolio!F11+$B$6 -> 0.15 | G19: =MIN(1,Portfolio!G11+$B$7) -> 1 | H19: =MAX(0,D19-E19*(1-F19)) -> 32.25 | I19: =H19*G19 -> 32.25
A20: =Portfolio!A12 -> Loan-03 | B20: =Portfolio!B12 -> Loans | C20: =Portfolio!C12 -> EFG Real Estate LLC | D20: =Portfolio!D12 -> 35 | E20: =IF(Portfolio!J12="Y",Portfolio!E12*(1+$B$5),Portfolio!E12) -> 10 | F20: =Portfolio!F12+$B$6 -> 0.15 | G20: =MIN(1,Portfolio!G12+$B$7) -> 1 | H20: =MAX(0,D20-E20*(1-F20)) -> 26.5 | I20: =H20*G20 -> 26.5
A21: =Portfolio!A13 -> Sec-01 | B21: =Portfolio!B13 -> Securitization | C21: =Portfolio!C13 -> HIJ ABS Tranche | D21: =Portfolio!D13 -> 25 | E21: =IF(Portfolio!J13="Y",Portfolio!E13*(1+$B$5),Portfolio!E13) -> 2.5 | F21: =Portfolio!F13+$B$6 -> 0.08 | G21: =MIN(1,Portfolio!G13+$B$7) -> 0.85 | H21: =MAX(0,D21-E21*(1-F21)) -> 22.7 | I21: =H21*G21 -> 19.295
... A25: =Portfolio!A17 -> Indem-03 | B25: =Portfolio!B17 -> Indemnified securities financing | C25: =Portfolio!C17 -> TUV Hedge Fund (borrower) | D25: =Portfolio!D17 -> 150 | E25: =IF(Portfolio!J17="Y",Portfolio!E17*(1+$B$5),Portfolio!E17) -> 79 | F25: =Portfolio!F17+$B$6 -> 0.07 | G25: =MIN(1,Portfolio!G17+$B$7) -> 0.3 | H25: =MAX(0,D25-E25*(1-F25)) -> 76.53 | I25: =H25*G25 -> 22.959
C27: TOTAL STRESSED RWA | I27: =SUM(I10:I25) -> 382.649
A30: Stressed CET1 capital rollforward
A31: Beginning CET1 Capital ($M) | B31: =Capital_Summary!B4 -> 24.5 | C31: Baseline CET1 Capital from Capital_Summary
A32: + Net income under stress ($M) | B32: 1.5 | C32: Illustrative: PPNR still positive but much lower under stress (per DFAST driver logic)
A33: - Trading & counterparty losses ($M) | B33: -3 | C33: Illustrative: losses from the Counterparty Default Scenario component
A34: - Other credit losses ($M) | B34: -1 | C34: Illustrative: incremental provisioning as unemployment/GDP assumptions bite
A35: Ending Stressed CET1 Capital ($M) | B35: =B31+B32+B33+B34 -> 22
A37: Stressed CET1 Ratio | B37: =B35/I27 -> 0.057493944
A38: Baseline CET1 Ratio (for comparison) | B38: =Capital_Summary!B5 -> 0.10809499
A39: Regulatory minimum (Basel III) | B39: 0.045
B41: Stressed RWA by category
B42: Indemnified securities financing | I42: =SUMIF(B10:B25,B42,I10:I25) -> 102.792
B43: Loans | I43: =SUMIF(B10:B25,B43,I10:I25) -> 101.75
B44: OTC derivatives | I44: =SUMIF(B10:B25,B44,I10:I25) -> 128.85
B45: Repo-style transactions | I45: =SUMIF(B10:B25,B45,I10:I25) -> 14.526
B46: Securitization | I46: =SUMIF(B10:B25,B46,I10:I25) -> 34.731

Sheet Basel_III_Endgame
A1: Current Basel III vs. Basel III Endgame
A2: Correction from an earlier draft of this workbook: a flat risk-weight cut on derivatives/securitization was NOT the right mechanism. The real driver for a custody bank like State Street is that Endgame adds two BRAND NEW capital charges that don't exist under current Basel III: (1) Operational Risk RWA, based on a 'Business Indicator' built largely from FEE income - State Street itself flagged this as a major concern in its own SEC filings, since custody banks earn most revenue from fees; and (2) a CVA (Credit Valuation Adjustment) charge on derivatives. The 2023 draft measured fee income on a GROSS basis (no netting) - the March 2026 re-proposal softens this to a NET basis, which is a real, specific relief for fee-heavy banks. Figures below are illustrative mock numbers, not State Street's actual revenue or capital impact.
A4: Business Indicator inputs (mock, illustrative)
A5: Interest income component ($M) | B5: 5 | E5: Illustrative - proxy for NII on this mock book
A6: Fee (services) income ($M) | B6: 20 | E6: Sized to reflect a fee-heavy, custody-style business
A7: Fee (services) expenses ($M) | B7: 12 | E7: Cost of providing those fee services
A8: Financial component ($M) | B8: 2 | E8: Illustrative - trading P&L component of the BI
A10: Business Indicator (BI)
B11: 2023 draft (gross) | C11: 2026 re-proposal (net) | E11: Note
A12: Services leg | B12: =B6+B7 -> 32 | C12: =B6-B7 -> 8 | E12: 2023: fee income + fee expenses, no netting. 2026: netted.
A13: Interest leg | B13: =B5 -> 5 | C13: =B5 -> 5
A14: Financial leg | B14: =B8 -> 2 | C14: =B8 -> 2
A15: Total BI | B15: =B12+B13+B14 -> 39 | C15: =C12+C13+C14 -> 15
A17: Marginal coefficient (illustrative single bucket) | B17: 0.12 | E17: Real rule uses tiered coefficients (12%/15%/18%) by BI size - simplified to one bucket here
A18: Internal Loss Multiplier (ILM) | B18: 1 | E18: Proposal floors ILM at 1 - no credit for a clean loss history
A20: Operational Risk RWA = 12.5 x BI x coefficient x ILM
A21: 2023 draft (gross BI) | B21: =12.5*B15*B17*B18 -> 58.5
A22: 2026 re-proposal (net BI) | B22: =12.5*C15*B17*B18 -> 22.5
A24: CVA charge, as % of Derivatives RWA (illustrative) | B24: 0.2 | E24: Brand new charge under Endgame for derivatives counterparty mark-to-market risk
A25: CVA RWA - baseline | B25: =Portfolio!I25*B24 -> 19.99
A26: CVA RWA - stressed | B26: =Stress_Scenario!I44*B24 -> 25.77
A28: Total RWA by framework
A29: Framework | B29: Baseline RWA ($M) | C29: Stressed RWA ($M)
A30: Current Basel III | B30: =Portfolio!I19 -> 226.6525 | C30: =Stress_Scenario!I27 -> 382.649
A31: Endgame - 2023 draft (gross BI) | B31: =Portfolio!I19+B25+B21 -> 305.1425 | C31: =Stress_Scenario!I27+B26+B21 -> 466.919
A32: Endgame - 2026 re-proposal (net BI) | B32: =Portfolio!I19+B25+B22 -> 269.1425 | C32: =Stress_Scenario!I27+B26+B22 -> 430.919
A34: CET1 Ratio comparison
A35: Scenario | B35: Total RWA ($M) | C35: CET1 Capital ($M) | D35: CET1 Ratio
A36: Current Basel III - Baseline | B36: =B30 -> 226.6525 | C36: =Capital_Summary!B4 -> 24.5 | D36: =C36/B36 -> 0.10809499
A37: Current Basel III - Stressed | B37: =C30 -> 382.649 | C37: =Stress_Scenario!B35 -> 22 | D37: =C37/B37 -> 0.057493944
A38: Endgame 2023 draft - Baseline | B38: =B31 -> 305.1425 | C38: =Capital_Summary!B4 -> 24.5 | D38: =C38/B38 -> 0.080290356
A39: Endgame 2023 draft - Stressed | B39: =C31 -> 466.919 | C39: =Stress_Scenario!B35 -> 22 | D39: =C39/B39 -> 0.04711738
A40: Endgame 2026 re-proposal - Baseline | B40: =B32 -> 269.1425 | C40: =Capital_Summary!B4 -> 24.5 | D40: =C40/B40 -> 0.091029845
A41: Endgame 2026 re-proposal - Stressed | B41: =C32 -> 430.919 | C41: =Stress_Scenario!B35 -> 22 | D41: =C41/B41 -> 0.051053678
A43: Regulatory minimum (Basel III): 4.5% - same floor applies under all frameworks
