Workbook

Sheet README
A1: Mock State Street Markets Capital & RWA Model
A3: Purpose of the Project
A4: A small exercise I built to actually understand how RWA and CET1
A5: ratios work, using a mock portfolio shaped like State Street Markets'
A6: real business (repo, securities lending, derivatives). Built this
A7: mainly to prep for a Capital Optimization Analyst role
A8: reading about Basel III wasn't clicking until I tried building the math myself.
A10: Basel III Endgame comparison
A11: Regulators put out a re-proposed Basel III Endgame rule in March 2026
A12: that's expected to ease up capital requirements a bit compared to the
A13: 2023 version (still not final as of this workbook). Since this directly
A14: affects the kind of work this role does, I'm adding a side-by-side:
... A27: - the Basel III Endgame risk-weight adjustment (illustrative only)
A29: Sources | B29: Link
A30: State Street 10-Q, June 30 2026 (RWA Roll-Forward table, Note 9 on Indemnified Securities Financing, repo/sec-lending maturity table) | B30: https://www.sec.gov/Archives/edgar/data/0000093751/000009375126000397/stt-20260630.htm
A31: State Street 2025 Dodd-Frank Act Stress Test Disclosure, July 1 2025 (Severely Adverse scenario assumptions) | B31: https://s203.q4cdn.com/888565246/files/doc_downloads/Dodd_Frank/2025/2025-Federal-Reserve-Stress-Test-Disclosure-vfinal.pdf
A32: State Street 2Q26 Earnings Release Addendum (real CET1, RWA used to sanity-check the model) | B32: https://s203.q4cdn.com/888565246/files/doc_financials/2026/q2/STT-2Q26-Earnings-Release-Addendum-vFinal.pdf
A33: Federal Reserve press release, March 19 2026, on the Basel III Endgame re-proposal (used for direction/magnitude only, not exact figures) | B33: https://www.federalreserve.gov/newsevents/pressreleases/bcreg20260319a.htm
A35: What's in each sheet:
A36: 1. Portfolio: the mock transactions, with live RWA formulas
A37: 2. Capital_Summary: baseline CET1 ratio + check against the real number
A38: 3. Stress_Scenario: Severely Adverse shocks applied, stressed CET1 ratio
A39: 4. Basel_III_Endgame: current rules vs. the proposed rules, side by side

Sheet Portfolio
A1: ID | B1: Category | C1: Counterparty (mock) | D1: Exposure ($M) | E1: Collateral ($M) | F1: Haircut (%) | G1: Risk Weight (%) | H1: E* = Exposure net of collateral ($M) | I1: RWA ($M) | J1: Collateral is equity type?
A2: Repo-01 | B2: Repo-style transactions | C2: ABC Broker-Dealer | D2: 420 | E2: 435 | F2: 0.02 | G2: 0.2 | H2: =MAX(0,D2-E2*(1-F2)) -> 0 | I2: =H2*G2 -> 0 | J2: N
A3: Repo-02 | B3: Repo-style transactions | C3: DEF Broker-Dealer | D3: 310 | E3: 318 | F3: 0.02 | G3: 0.2 | H3: =MAX(0,D3-E3*(1-F3)) -> 0 | I3: =H3*G3 -> 0 | J3: N
A4: Repo-03 | B4: Repo-style transactions | C4: GHI Sponsored Repo Client (FICC) | D4: 260 | E4: 268 | F4: 0.02 | G4: 0.2 | H4: =MAX(0,D4-E4*(1-F4)) -> 0 | I4: =H4*G4 -> 0 | J4: N
A5: Repo-04 | B5: Repo-style transactions | C5: JKL Sponsored Repo Client (FICC) | D5: 180 | E5: 185 | F5: 0.02 | G5: 0.2 | H5: =MAX(0,D5-E5*(1-F5)) -> 0 | I5: =H5*G5 -> 0 | J5: N
A6: Deriv-01 | B6: OTC derivatives | C6: MNO Asset Manager - FX fwd | D6: 150 | E6: 90 | F6: 0.05 | G6: 0.5 | H6: =MAX(0,D6-E6*(1-F6)) -> 64.5 | I6: =H6*G6 -> 32.25 | J6: N
A7: Deriv-02 | B7: OTC derivatives | C7: PQR Asset Manager - FX swap | D7: 130 | E7: 70 | F7: 0.05 | G7: 0.5 | H7: =MAX(0,D7-E7*(1-F7)) -> 63.5 | I7: =H7*G7 -> 31.75 | J7: N
A8: Deriv-03 | B8: OTC derivatives | C8: STU Pension Fund - IR swap | D8: 95 | E8: 40 | F8: 0.05 | G8: 0.5 | H8: =MAX(0,D8-E8*(1-F8)) -> 57 | I8: =H8*G8 -> 28.5 | J8: N
A9: Deriv-04 | B9: OTC derivatives | C9: VWX Sovereign Fund - FX fwd | D9: 80 | E9: 45 | F9: 0.05 | G9: 0.2 | H9: =MAX(0,D9-E9*(1-F9)) -> 37.25 | I9: =H9*G9 -> 7.45 | J9: N
A10: Loan-01 | B10: Loans | C10: YZ Corp | D10: 60 | E10: 20 | F10: 0.1 | G10: 1 | H10: =MAX(0,D10-E10*(1-F10)) -> 42 | I10: =H10*G10 -> 42 | J10: N
A11: Loan-02 | B11: Loans | C11: 12 Corp | D11: 45 | E11: 15 | F11: 0.1 | G11: 1 | H11: =MAX(0,D11-E11*(1-F11)) -> 31.5 | I11: =H11*G11 -> 31.5 | J11: N
A12: Loan-03 | B12: Loans | C12: 34 Real Estate LLC | D12: 35 | E12: 10 | F12: 0.1 | G12: 1 | H12: =MAX(0,D12-E12*(1-F12)) -> 26 | I12: =H12*G12 -> 26 | J12: N
A13: Sec-01 | B13: Securitization | C13: 56 ABS Tranche | D13: 25 | E13: 5 | F13: 0.03 | G13: 0.75 | H13: =MAX(0,D13-E13*(1-F13)) -> 20.15 | I13: =H13*G13 -> 15.1125 | J13: Y
... A17: Indem-03 | B17: Indemnified securities financing | C17: 12 Hedge Fund (borrower) | D17: 150 | E17: 158 | F17: 0.02 | G17: 0.2 | H17: =MAX(0,D17-E17*(1-F17)) -> 0 | I17: =H17*G17 -> 0 | J17: Y
H18: =_xlfn.FORMULATEXT(H2) -> =MAX(0,D2-E2*(1-F2)) | I18: =_xlfn.FORMULATEXT(I2) -> =H2*G2
C20: TOTAL PORTFOLIO | D20: =SUM(D2:D17) -> 2480 | E20: =SUM(E2:E17) -> 2209 | H20: =SUM(H2:H18) -> 358.02 | I20: =SUM(I2:I17) -> 226.6525
B23: RWA by category | J23: % of total RWA
B24: Indemnified securities financing | I24: =SUMIF(B2:B17,B24,I2:I17) -> 0 | J24: =I24/$I$20 -> 0
B25: Loans | I25: =SUMIF(B2:B17,B25,I2:I17) -> 99.5 | J25: =I25/$I$20 -> 0.43899803
B26: OTC derivatives | I26: =SUMIF(B2:B17,B26,I2:I17) -> 99.95 | J26: =I26/$I$20 -> 0.44098344
B27: Repo-style transactions | I27: =SUMIF(B2:B17,B27,I2:I17) -> 0 | J27: =I27/$I$20 -> 0
B28: Securitization | I28: =SUMIF(B2:B17,B28,I2:I17) -> 27.2025 | J28: =I28/$I$20 -> 0.12001853
I29: =_xlfn.FORMULATEXT(I28) -> =SUMIF(B2:B17,B28,I2:I17) | J29: =_xlfn.FORMULATEXT(J28) -> =I28/$I$20
B32: NOTES
B33: Exposure | C33: The amount at risk if the counterparty doesn't pay it back.
B34: Collateral | C34: What the counterparty pledges as security for that amount.
B35: Haircut | C35: A safety discount on collateral value, since it could lose value before it's sold. Higher haircut = collateral is trusted less.
B36: Risk Weight | C36: A regulator set multiplier for how risky that counterparty/collateral type is.
B37: E* (Exposure net of collateral) | C37: What's actually at risk after subtracting trusted collateral value. RWA is calculated from this, not the raw exposure.
B38: RWA | C38: E* x Risk Weight - the number capital requirements are based on.
B40: E* = MAX(0, Exposure - Collateral×(1-Haircut)) | C40: If the counterparty disappeared right now, how much would we actually lose after subtracting the trusted collateral?"
B42: A= Collateral×(1-Haircut) | C42: Hair cut: safety discount
C43: even though the collateral is worth $435M on paper
C44: we only "trust" $426.3M of it because we're discounting 2% in case
C45: its value drops before we can sell it.
B46: E* = Exposure - [A] | C46: how much we lent minus the trusted collateral value we just calculated

Sheet Capital_Summary
A1: Capital Summary - Baseline (no stress)
A3: Total RWA ($M) | B3: =Portfolio!I20 -> 226.6525 | C3: Sum of mock portfolio RWA (Portfolio sheet)
A4: CET1 Capital ($M) - assumption | B4: 24.5 | C4: Set so baseline CET1 ratio lands near State Street's real 2Q26 ratio (~10.8%) for calibration
A5: CET1 Ratio | B5: =B4/B3 -> 0.10809499 | C5: CET1 Ratio = CET1 Capital / Total RWA
A7: Calibration check
A8: Real State Street CET1 Ratio, 2Q26 (Standardized) | B8: 0.108 | C8: Real State Street CET1 Ratio (2Q26, per their actual earnings release): 10.8%
A9: Difference (mock model vs real) | B9: =B5-B8 -> 9.4991231e-05 | C9: Difference between mock model and the real number: 0.0%
A11: RWA composition check vs real 10-Q roll-forward
A12: Real: Credit risk RWA, % of total (2Q26 Standardized) | B12: 0.981 | C12: $140,668M credit / $143,406M total. Source: 10-Q Table, June 30 2026
A13: Mock model: RWA in credit-risk-style categories, % of total | B13: =(Portfolio!I25+Portfolio!I26+Portfolio!I27+Portfolio!I28+Portfolio!I24)/Portfolio!I20 -> 1 | C13: All mock categories are credit-risk-style, so this should read ~100%

Sheet Stress_Scenario
A1: Stress Scenario - Supervisory Severely Adverse
A2: Source: State Street 2025 DFAST Disclosure (Severely Adverse scenario: unemployment 10%, real GDP -7.8%, equity market -50%). Row-level shocks below are my own simplified way of applying those macro assumptions to this mock portfolio - not State Street's actual stress methodology.
A4: Stress assumptions
A5: Equity market shock (Severely Adverse) | B5: -0.5 | C5: DFAST 2025: equity market decline of 50% over the 9-quarter horizon
A6: Haircut add-on under stress | B6: 0.05 | C6: Illustrative: wider haircuts as market liquidity deteriorates
A7: Risk weight add-on under stress | B7: 0.1 | C7: Illustrative: credit migration as unemployment rises to 10%, GDP falls 7.8%
A9: ID | B9: Category | C9: Counterparty (mock) | D9: Exposure ($M) | E9: Stressed Collateral ($M) | F9: Stressed Haircut (%) | G9: Stressed Risk Weight (%) | H9: Stressed E* ($M) | I9: Stressed RWA ($M)
A10: =Portfolio!A2 -> Repo-01 | B10: =Portfolio!B2 -> Repo-style transactions | C10: =Portfolio!C2 -> ABC Broker-Dealer | D10: =Portfolio!D2 -> 420 | E10: =IF(Portfolio!J2="Y",Portfolio!E2*(1+$B$5),Portfolio!E2) -> 435 | F10: =Portfolio!F2+$B$6 -> 0.07 | G10: =MIN(1,Portfolio!G2+$B$7) -> 0.3 | H10: =MAX(0,D10-E10*(1-F10)) -> 15.45 | I10: =H10*G10 -> 4.635
A11: =Portfolio!A3 -> Repo-02 | B11: =Portfolio!B3 -> Repo-style transactions | C11: =Portfolio!C3 -> DEF Broker-Dealer | D11: =Portfolio!D3 -> 310 | E11: =IF(Portfolio!J3="Y",Portfolio!E3*(1+$B$5),Portfolio!E3) -> 318 | F11: =Portfolio!F3+$B$6 -> 0.07 | G11: =MIN(1,Portfolio!G3+$B$7) -> 0.3 | H11: =MAX(0,D11-E11*(1-F11)) -> 14.26 | I11: =H11*G11 -> 4.278
A12: =Portfolio!A4 -> Repo-03 | B12: =Portfolio!B4 -> Repo-style transactions | C12: =Portfolio!C4 -> GHI Sponsored Repo Client (FICC) | D12: =Portfolio!D4 -> 260 | E12: =IF(Portfolio!J4="Y",Portfolio!E4*(1+$B$5),Portfolio!E4) -> 268 | F12: =Portfolio!F4+$B$6 -> 0.07 | G12: =MIN(1,Portfolio!G4+$B$7) -> 0.3 | H12: =MAX(0,D12-E12*(1-F12)) -> 10.76 | I12: =H12*G12 -> 3.228
A13: =Portfolio!A5 -> Repo-04 | B13: =Portfolio!B5 -> Repo-style transactions | C13: =Portfolio!C5 -> JKL Sponsored Repo Client (FICC) | D13: =Portfolio!D5 -> 180 | E13: =IF(Portfolio!J5="Y",Portfolio!E5*(1+$B$5),Portfolio!E5) -> 185 | F13: =Portfolio!F5+$B$6 -> 0.07 | G13: =MIN(1,Portfolio!G5+$B$7) -> 0.3 | H13: =MAX(0,D13-E13*(1-F13)) -> 7.95 | I13: =H13*G13 -> 2.385
A14: =Portfolio!A6 -> Deriv-01 | B14: =Portfolio!B6 -> OTC derivatives | C14: =Portfolio!C6 -> MNO Asset Manager - FX fwd | D14: =Portfolio!D6 -> 150 | E14: =IF(Portfolio!J6="Y",Portfolio!E6*(1+$B$5),Portfolio!E6) -> 90 | F14: =Portfolio!F6+$B$6 -> 0.1 | G14: =MIN(1,Portfolio!G6+$B$7) -> 0.6 | H14: =MAX(0,D14-E14*(1-F14)) -> 69 | I14: =H14*G14 -> 41.4
A15: =Portfolio!A7 -> Deriv-02 | B15: =Portfolio!B7 -> OTC derivatives | C15: =Portfolio!C7 -> PQR Asset Manager - FX swap | D15: =Portfolio!D7 -> 130 | E15: =IF(Portfolio!J7="Y",Portfolio!E7*(1+$B$5),Portfolio!E7) -> 70 | F15: =Portfolio!F7+$B$6 -> 0.1 | G15: =MIN(1,Portfolio!G7+$B$7) -> 0.6 | H15: =MAX(0,D15-E15*(1-F15)) -> 67 | I15: =H15*G15 -> 40.2
A16: =Portfolio!A8 -> Deriv-03 | B16: =Portfolio!B8 -> OTC derivatives | C16: =Portfolio!C8 -> STU Pension Fund - IR swap | D16: =Portfolio!D8 -> 95 | E16: =IF(Portfolio!J8="Y",Portfolio!E8*(1+$B$5),Portfolio!E8) -> 40 | F16: =Portfolio!F8+$B$6 -> 0.1 | G16: =MIN(1,Portfolio!G8+$B$7) -> 0.6 | H16: =MAX(0,D16-E16*(1-F16)) -> 59 | I16: =H16*G16 -> 35.4
A17: =Portfolio!A9 -> Deriv-04 | B17: =Portfolio!B9 -> OTC derivatives | C17: =Portfolio!C9 -> VWX Sovereign Fund - FX fwd | D17: =Portfolio!D9 -> 80 | E17: =IF(Portfolio!J9="Y",Portfolio!E9*(1+$B$5),Portfolio!E9) -> 45 | F17: =Portfolio!F9+$B$6 -> 0.1 | G17: =MIN(1,Portfolio!G9+$B$7) -> 0.3 | H17: =MAX(0,D17-E17*(1-F17)) -> 39.5 | I17: =H17*G17 -> 11.85
A18: =Portfolio!A10 -> Loan-01 | B18: =Portfolio!B10 -> Loans | C18: =Portfolio!C10 -> YZ Corp | D18: =Portfolio!D10 -> 60 | E18: =IF(Portfolio!J10="Y",Portfolio!E10*(1+$B$5),Portfolio!E10) -> 20 | F18: =Portfolio!F10+$B$6 -> 0.15 | G18: =MIN(1,Portfolio!G10+$B$7) -> 1 | H18: =MAX(0,D18-E18*(1-F18)) -> 43 | I18: =H18*G18 -> 43
A19: =Portfolio!A11 -> Loan-02 | B19: =Portfolio!B11 -> Loans | C19: =Portfolio!C11 -> 12 Corp | D19: =Portfolio!D11 -> 45 | E19: =IF(Portfolio!J11="Y",Portfolio!E11*(1+$B$5),Portfolio!E11) -> 15 | F19: =Portfolio!F11+$B$6 -> 0.15 | G19: =MIN(1,Portfolio!G11+$B$7) -> 1 | H19: =MAX(0,D19-E19*(1-F19)) -> 32.25 | I19: =H19*G19 -> 32.25
A20: =Portfolio!A12 -> Loan-03 | B20: =Portfolio!B12 -> Loans | C20: =Portfolio!C12 -> 34 Real Estate LLC | D20: =Portfolio!D12 -> 35 | E20: =IF(Portfolio!J12="Y",Portfolio!E12*(1+$B$5),Portfolio!E12) -> 10 | F20: =Portfolio!F12+$B$6 -> 0.15 | G20: =MIN(1,Portfolio!G12+$B$7) -> 1 | H20: =MAX(0,D20-E20*(1-F20)) -> 26.5 | I20: =H20*G20 -> 26.5
A21: =Portfolio!A13 -> Sec-01 | B21: =Portfolio!B13 -> Securitization | C21: =Portfolio!C13 -> 56 ABS Tranche | D21: =Portfolio!D13 -> 25 | E21: =IF(Portfolio!J13="Y",Portfolio!E13*(1+$B$5),Portfolio!E13) -> 2.5 | F21: =Portfolio!F13+$B$6 -> 0.08 | G21: =MIN(1,Portfolio!G13+$B$7) -> 0.85 | H21: =MAX(0,D21-E21*(1-F21)) -> 22.7 | I21: =H21*G21 -> 19.295
... A25: =Portfolio!A17 -> Indem-03 | B25: =Portfolio!B17 -> Indemnified securities financing | C25: =Portfolio!C17 -> 12 Hedge Fund (borrower) | D25: =Portfolio!D17 -> 150 | E25: =IF(Portfolio!J17="Y",Portfolio!E17*(1+$B$5),Portfolio!E17) -> 79 | F25: =Portfolio!F17+$B$6 -> 0.07 | G25: =MIN(1,Portfolio!G17+$B$7) -> 0.3 | H25: =MAX(0,D25-E25*(1-F25)) -> 76.53 | I25: =H25*G25 -> 22.959
E26: Stressed Collateral = Collateral × (1 + Equity Shock) | F26: Stressed Haircut = Haircut + Haircut Add-on | G26: Stressed Risk Weight = MIN(100%, Risk Weight + Risk Weight Add-on) | H26: Stressed E* (Effective Exposure) = MAX(0, Exposure − Collateral × (1 − Haircut)) | I26: Stressed RWA = E* × Risk Weight
E27: =_xlfn.FORMULATEXT(E25) -> =IF(Portfolio!J17="Y",Portfolio!E17*(1+$B$5),Portfolio!E17) | F27: =_xlfn.FORMULATEXT(F25) -> =Portfolio!F17+$B$6 | G27: =_xlfn.FORMULATEXT(G25) -> =MIN(1,Portfolio!G17+$B$7) | H27: =_xlfn.FORMULATEXT(H25) -> =MAX(0,D25-E25*(1-F25)) | I27: =_xlfn.FORMULATEXT(I25) -> =H25*G25
C28: TOTAL STRESSED RWA | I28: =SUM(I10:I25) -> 382.649
A31: Stressed CET1 capital rollforward
A32: Beginning CET1 Capital ($M) | B32: =Capital_Summary!B4 -> 24.5 | C32: Baseline CET1 Capital from Capital_Summary
A33: + Net income under stress ($M) | B33: 1.5 | C33: Illustrative: PPNR still positive but much lower under stress (per DFAST driver logic)
A34: - Trading & counterparty losses ($M) | B34: -3 | C34: Illustrative: losses from the Counterparty Default Scenario component
A35: - Other credit losses ($M) | B35: -1 | C35: Illustrative: incremental provisioning as unemployment/GDP assumptions bite
A36: Ending Stressed CET1 Capital ($M) | B36: =B32+B33+B34+B35 -> 22
A38: Stressed CET1 Ratio | B38: =B36/I28 -> 0.057493944
A39: Baseline CET1 Ratio (for comparison) | B39: =Capital_Summary!B5 -> 0.10809499
A40: Regulatory minimum (Basel III) | B40: 0.045
B42: Stressed RWA by category
B43: Indemnified securities financing | I43: =SUMIF(B10:B25,B43,I10:I25) -> 102.792 | J43: =_xlfn.FORMULATEXT(I43) -> =SUMIF(B10:B25,B43,I10:I25)
B44: Loans | I44: =SUMIF(B10:B25,B44,I10:I25) -> 101.75 | J44: =_xlfn.FORMULATEXT(I44) -> =SUMIF(B10:B25,B44,I10:I25)
B45: OTC derivatives | I45: =SUMIF(B10:B25,B45,I10:I25) -> 128.85 | J45: =_xlfn.FORMULATEXT(I45) -> =SUMIF(B10:B25,B45,I10:I25)
B46: Repo-style transactions | I46: =SUMIF(B10:B25,B46,I10:I25) -> 14.526 | J46: =_xlfn.FORMULATEXT(I46) -> =SUMIF(B10:B25,B46,I10:I25)
B47: Securitization | I47: =SUMIF(B10:B25,B47,I10:I25) -> 34.731 | J47: =_xlfn.FORMULATEXT(I47) -> =SUMIF(B10:B25,B47,I10:I25)

Sheet Basel_III_Endgame
A1: Current Basel III vs. Basel III Endgame
A2: Correction from an earlier draft of this workbook: a flat risk-weight cut on derivatives/securitization was NOT the right mechanism. The real driver for a custody bank like State Street is that Endgame adds two BRAND NEW capital charges that don't exist under current Basel III: (1) Operational Risk RWA, based on a 'Business Indicator' built largely from FEE income, State Street itself flagged this as a major concern in its own SEC filings, since custody banks earn most revenue from fees; and (2) a CVA (Credit Valuation Adjustment) charge on derivatives. The 2023 draft measured fee income on a GROSS basis (no netting) the March 2026 reproposal softens this to a NET basis, which is a real, specific relief for fee heavy banks. Figures below are illustrative mock numbers, not State Street's actual revenue or capital impact.
A4: Business Indicator inputs (mock, illustrative)
A5: Interest income component ($M) | B5: 5 | E5: Illustrative proxy for NII on this mock book
A6: Fee (services) income ($M) | B6: 20 | E6: Sized to reflect a fee heavy, custody style business
A7: Fee (services) expenses ($M) | B7: 12 | E7: Cost of providing those fee services
A8: Financial component ($M) | B8: 2 | E8: Illustrative trading P&L component of the BI
A10: Business Indicator (BI)
B11: 2023 draft (gross) | C11: 2026 re-proposal (net) | E11: Note
A12: Services leg | B12: =B6+B7 -> 32 | C12: =B6-B7 -> 8 | E12: 2023: fee income + fee expenses, no netting. 2026: netted.
A13: Interest leg | B13: =B5 -> 5 | C13: =B5 -> 5
A14: Financial leg | B14: =B8 -> 2 | C14: =B8 -> 2
A15: Total BI | B15: =B12+B13+B14 -> 39 | C15: =C12+C13+C14 -> 15
A17: Marginal coefficient (illustrative single bucket) | B17: 0.12 | E17: Real rule uses tiered coefficients (12%/15%/18%) by BI size simplified to one bucket here
A18: Internal Loss Multiplier (ILM) | B18: 1 | E18: Proposal floors ILM at 1, no credit for a clean loss history
A20: Operational Risk RWA = 12.5 x BI x coefficient x ILM
A21: 2023 draft (gross BI) | B21: =12.5*B15*B17*B18 -> 58.5
A22: 2026 reproposal (net BI) | B22: =12.5*C15*B17*B18 -> 22.5
A24: CVA charge, as % of Derivatives RWA (illustrative) | B24: 0.2 | E24: Brand new charge under Endgame for derivatives counterparty mark-to-market risk
A25: CVA RWA - baseline | B25: =Portfolio!I26*B24 -> 19.99
A26: CVA RWA - stressed | B26: =Stress_Scenario!I45*B24 -> 25.77
A28: Total RWA by framework
A29: Framework | B29: Baseline RWA ($M) | C29: Stressed RWA ($M)
A30: Current Basel III | B30: =Portfolio!I20 -> 226.6525 | C30: =Stress_Scenario!I28 -> 382.649
A31: Endgame - 2023 draft (gross BI) | B31: =Portfolio!I20+B25+B21 -> 305.1425 | C31: =Stress_Scenario!I28+B26+B21 -> 466.919
A32: Endgame - 2026 reproposal (net BI) | B32: =Portfolio!I20+B25+B22 -> 269.1425 | C32: =Stress_Scenario!I28+B26+B22 -> 430.919
A34: CET1 Ratio comparison
A35: Scenario | B35: Total RWA ($M) | C35: CET1 Capital ($M) | D35: CET1 Ratio
A36: Current Basel III - Baseline | B36: =B30 -> 226.6525 | C36: =Capital_Summary!B4 -> 24.5 | D36: =C36/B36 -> 0.10809499
A37: Current Basel III - Stressed | B37: =C30 -> 382.649 | C37: =Stress_Scenario!B36 -> 22 | D37: =C37/B37 -> 0.057493944
A38: Endgame 2023 draft - Baseline | B38: =B31 -> 305.1425 | C38: =Capital_Summary!B4 -> 24.5 | D38: =C38/B38 -> 0.080290356
A39: Endgame 2023 draft - Stressed | B39: =C31 -> 466.919 | C39: =Stress_Scenario!B36 -> 22 | D39: =C39/B39 -> 0.04711738
A40: Endgame 2026 reproposal - Baseline | B40: =B32 -> 269.1425 | C40: =Capital_Summary!B4 -> 24.5 | D40: =C40/B40 -> 0.091029845
A41: Endgame 2026 reproposal - Stressed | B41: =C32 -> 430.919 | C41: =Stress_Scenario!B36 -> 22 | D41: =C41/B41 -> 0.051053678
A43: Regulatory minimum (Basel III): 4.5% - same floor applies under all frameworks

Sheet DATA
A1: ID | B1: Category | C1: Counterparty (mock) | D1: Scenario | E1: Exposure ($M) | F1: Collateral ($M) | G1: Haircut (%) | H1: Risk Weight (%) | I1: E* = Exposure net of collateral ($M) | J1: RWA ($M) | K1: Collateral is equity type?
A2: =[1]Portfolio!A2 -> Repo-01 | B2: =[1]Portfolio!B2 -> Repo-style transactions | C2: =[1]Portfolio!C2 -> ABC Broker-Dealer | D2: Baseline | E2: =[1]Portfolio!D2 -> 420 | F2: =[1]Portfolio!E2 -> 435 | G2: =[1]Portfolio!F2 -> 0.02 | H2: =[1]Portfolio!G2 -> 0.2 | I2: =[1]Portfolio!H2 -> 0 | J2: =[1]Portfolio!I2 -> 0 | K2: =[1]Portfolio!J2 -> N
A3: =[1]Portfolio!A3 -> Repo-02 | B3: =[1]Portfolio!B3 -> Repo-style transactions | C3: =[1]Portfolio!C3 -> DEF Broker-Dealer | D3: Baseline | E3: =[1]Portfolio!D3 -> 310 | F3: =[1]Portfolio!E3 -> 318 | G3: =[1]Portfolio!F3 -> 0.02 | H3: =[1]Portfolio!G3 -> 0.2 | I3: =[1]Portfolio!H3 -> 0 | J3: =[1]Portfolio!I3 -> 0 | K3: =[1]Portfolio!J3 -> N
A4: =[1]Portfolio!A4 -> Repo-03 | B4: =[1]Portfolio!B4 -> Repo-style transactions | C4: =[1]Portfolio!C4 -> GHI Sponsored Repo Client (FICC) | D4: Baseline | E4: =[1]Portfolio!D4 -> 260 | F4: =[1]Portfolio!E4 -> 268 | G4: =[1]Portfolio!F4 -> 0.02 | H4: =[1]Portfolio!G4 -> 0.2 | I4: =[1]Portfolio!H4 -> 0 | J4: =[1]Portfolio!I4 -> 0 | K4: =[1]Portfolio!J4 -> N
A5: =[1]Portfolio!A5 -> Repo-04 | B5: =[1]Portfolio!B5 -> Repo-style transactions | C5: =[1]Portfolio!C5 -> JKL Sponsored Repo Client (FICC) | D5: Baseline | E5: =[1]Portfolio!D5 -> 180 | F5: =[1]Portfolio!E5 -> 185 | G5: =[1]Portfolio!F5 -> 0.02 | H5: =[1]Portfolio!G5 -> 0.2 | I5: =[1]Portfolio!H5 -> 0 | J5: =[1]Portfolio!I5 -> 0 | K5: =[1]Portfolio!J5 -> N
A6: =[1]Portfolio!A6 -> Deriv-01 | B6: =[1]Portfolio!B6 -> OTC derivatives | C6: =[1]Portfolio!C6 -> MNO Asset Manager - FX fwd | D6: Baseline | E6: =[1]Portfolio!D6 -> 150 | F6: =[1]Portfolio!E6 -> 90 | G6: =[1]Portfolio!F6 -> 0.05 | H6: =[1]Portfolio!G6 -> 0.5 | I6: =[1]Portfolio!H6 -> 64.5 | J6: =[1]Portfolio!I6 -> 32.25 | K6: =[1]Portfolio!J6 -> N
A7: =[1]Portfolio!A7 -> Deriv-02 | B7: =[1]Portfolio!B7 -> OTC derivatives | C7: =[1]Portfolio!C7 -> PQR Asset Manager - FX swap | D7: Baseline | E7: =[1]Portfolio!D7 -> 130 | F7: =[1]Portfolio!E7 -> 70 | G7: =[1]Portfolio!F7 -> 0.05 | H7: =[1]Portfolio!G7 -> 0.5 | I7: =[1]Portfolio!H7 -> 63.5 | J7: =[1]Portfolio!I7 -> 31.75 | K7: =[1]Portfolio!J7 -> N
A8: =[1]Portfolio!A8 -> Deriv-03 | B8: =[1]Portfolio!B8 -> OTC derivatives | C8: =[1]Portfolio!C8 -> STU Pension Fund - IR swap | D8: Baseline | E8: =[1]Portfolio!D8 -> 95 | F8: =[1]Portfolio!E8 -> 40 | G8: =[1]Portfolio!F8 -> 0.05 | H8: =[1]Portfolio!G8 -> 0.5 | I8: =[1]Portfolio!H8 -> 57 | J8: =[1]Portfolio!I8 -> 28.5 | K8: =[1]Portfolio!J8 -> N
A9: =[1]Portfolio!A9 -> Deriv-04 | B9: =[1]Portfolio!B9 -> OTC derivatives | C9: =[1]Portfolio!C9 -> VWX Sovereign Fund - FX fwd | D9: Baseline | E9: =[1]Portfolio!D9 -> 80 | F9: =[1]Portfolio!E9 -> 45 | G9: =[1]Portfolio!F9 -> 0.05 | H9: =[1]Portfolio!G9 -> 0.2 | I9: =[1]Portfolio!H9 -> 37.25 | J9: =[1]Portfolio!I9 -> 7.45 | K9: =[1]Portfolio!J9 -> N
A10: =[1]Portfolio!A10 -> Loan-01 | B10: =[1]Portfolio!B10 -> Loans | C10: =[1]Portfolio!C10 -> YZ Corp | D10: Baseline | E10: =[1]Portfolio!D10 -> 60 | F10: =[1]Portfolio!E10 -> 20 | G10: =[1]Portfolio!F10 -> 0.1 | H10: =[1]Portfolio!G10 -> 1 | I10: =[1]Portfolio!H10 -> 42 | J10: =[1]Portfolio!I10 -> 42 | K10: =[1]Portfolio!J10 -> N
A11: =[1]Portfolio!A11 -> Loan-02 | B11: =[1]Portfolio!B11 -> Loans | C11: =[1]Portfolio!C11 -> 12 Corp | D11: Baseline | E11: =[1]Portfolio!D11 -> 45 | F11: =[1]Portfolio!E11 -> 15 | G11: =[1]Portfolio!F11 -> 0.1 | H11: =[1]Portfolio!G11 -> 1 | I11: =[1]Portfolio!H11 -> 31.5 | J11: =[1]Portfolio!I11 -> 31.5 | K11: =[1]Portfolio!J11 -> N
A12: =[1]Portfolio!A12 -> Loan-03 | B12: =[1]Portfolio!B12 -> Loans | C12: =[1]Portfolio!C12 -> 34 Real Estate LLC | D12: Baseline | E12: =[1]Portfolio!D12 -> 35 | F12: =[1]Portfolio!E12 -> 10 | G12: =[1]Portfolio!F12 -> 0.1 | H12: =[1]Portfolio!G12 -> 1 | I12: =[1]Portfolio!H12 -> 26 | J12: =[1]Portfolio!I12 -> 26 | K12: =[1]Portfolio!J12 -> N
A13: =[1]Portfolio!A13 -> Sec-01 | B13: =[1]Portfolio!B13 -> Securitization | C13: =[1]Portfolio!C13 -> 56 ABS Tranche | D13: Baseline | E13: =[1]Portfolio!D13 -> 25 | F13: =[1]Portfolio!E13 -> 5 | G13: =[1]Portfolio!F13 -> 0.03 | H13: =[1]Portfolio!G13 -> 0.75 | I13: =[1]Portfolio!H13 -> 20.15 | J13: =[1]Portfolio!I13 -> 15.1125 | K13: =[1]Portfolio!J13 -> Y
... A17: =[1]Portfolio!A17 -> Indem-03 | B17: =[1]Portfolio!B17 -> Indemnified securities financing | C17: =[1]Portfolio!C17 -> 12 Hedge Fund (borrower) | D17: Baseline | E17: =[1]Portfolio!D17 -> 150 | F17: =[1]Portfolio!E17 -> 158 | G17: =[1]Portfolio!F17 -> 0.02 | H17: =[1]Portfolio!G17 -> 0.2 | I17: =[1]Portfolio!H17 -> 0 | J17: =[1]Portfolio!I17 -> 0 | K17: =[1]Portfolio!J17 -> Y
A18: =[1]Stress_Scenario!A10 -> Repo-01 | B18: =[1]Stress_Scenario!B10 -> Repo-style transactions | C18: =[1]Stress_Scenario!C10 -> ABC Broker-Dealer | D18: Stressed | E18: =[1]Stress_Scenario!D10 -> 420 | F18: =[1]Stress_Scenario!E10 -> 435 | G18: =[1]Stress_Scenario!F10 -> 0.07 | H18: =[1]Stress_Scenario!G10 -> 0.3 | I18: =[1]Stress_Scenario!H10 -> 15.45 | J18: =[1]Stress_Scenario!I10 -> 4.635 | K18: =INDEX([1]Portfolio!$J$2:$J$17,MATCH(A18,[1]Portfolio!$A$2:$A$17,0)) -> N
A19: =[1]Stress_Scenario!A11 -> Repo-02 | B19: =[1]Stress_Scenario!B11 -> Repo-style transactions | C19: =[1]Stress_Scenario!C11 -> DEF Broker-Dealer | D19: Stressed | E19: =[1]Stress_Scenario!D11 -> 310 | F19: =[1]Stress_Scenario!E11 -> 318 | G19: =[1]Stress_Scenario!F11 -> 0.07 | H19: =[1]Stress_Scenario!G11 -> 0.3 | I19: =[1]Stress_Scenario!H11 -> 14.26 | J19: =[1]Stress_Scenario!I11 -> 4.278 | K19: =INDEX([1]Portfolio!$J$2:$J$17,MATCH(A19,[1]Portfolio!$A$2:$A$17,0)) -> N
A20: =[1]Stress_Scenario!A12 -> Repo-03 | B20: =[1]Stress_Scenario!B12 -> Repo-style transactions | C20: =[1]Stress_Scenario!C12 -> GHI Sponsored Repo Client (FICC) | D20: Stressed | E20: =[1]Stress_Scenario!D12 -> 260 | F20: =[1]Stress_Scenario!E12 -> 268 | G20: =[1]Stress_Scenario!F12 -> 0.07 | H20: =[1]Stress_Scenario!G12 -> 0.3 | I20: =[1]Stress_Scenario!H12 -> 10.76 | J20: =[1]Stress_Scenario!I12 -> 3.228 | K20: =INDEX([1]Portfolio!$J$2:$J$17,MATCH(A20,[1]Portfolio!$A$2:$A$17,0)) -> N
A21: =[1]Stress_Scenario!A13 -> Repo-04 | B21: =[1]Stress_Scenario!B13 -> Repo-style transactions | C21: =[1]Stress_Scenario!C13 -> JKL Sponsored Repo Client (FICC) | D21: Stressed | E21: =[1]Stress_Scenario!D13 -> 180 | F21: =[1]Stress_Scenario!E13 -> 185 | G21: =[1]Stress_Scenario!F13 -> 0.07 | H21: =[1]Stress_Scenario!G13 -> 0.3 | I21: =[1]Stress_Scenario!H13 -> 7.95 | J21: =[1]Stress_Scenario!I13 -> 2.385 | K21: =INDEX([1]Portfolio!$J$2:$J$17,MATCH(A21,[1]Portfolio!$A$2:$A$17,0)) -> N
A22: =[1]Stress_Scenario!A14 -> Deriv-01 | B22: =[1]Stress_Scenario!B14 -> OTC derivatives | C22: =[1]Stress_Scenario!C14 -> MNO Asset Manager - FX fwd | D22: Stressed | E22: =[1]Stress_Scenario!D14 -> 150 | F22: =[1]Stress_Scenario!E14 -> 90 | G22: =[1]Stress_Scenario!F14 -> 0.1 | H22: =[1]Stress_Scenario!G14 -> 0.6 | I22: =[1]Stress_Scenario!H14 -> 69 | J22: =[1]Stress_Scenario!I14 -> 41.4 | K22: =INDEX([1]Portfolio!$J$2:$J$17,MATCH(A22,[1]Portfolio!$A$2:$A$17,0)) -> N
A23: =[1]Stress_Scenario!A15 -> Deriv-02 | B23: =[1]Stress_Scenario!B15 -> OTC derivatives | C23: =[1]Stress_Scenario!C15 -> PQR Asset Manager - FX swap | D23: Stressed | E23: =[1]Stress_Scenario!D15 -> 130 | F23: =[1]Stress_Scenario!E15 -> 70 | G23: =[1]Stress_Scenario!F15 -> 0.1 | H23: =[1]Stress_Scenario!G15 -> 0.6 | I23: =[1]Stress_Scenario!H15 -> 67 | J23: =[1]Stress_Scenario!I15 -> 40.2 | K23: =INDEX([1]Portfolio!$J$2:$J$17,MATCH(A23,[1]Portfolio!$A$2:$A$17,0)) -> N
A24: =[1]Stress_Scenario!A16 -> Deriv-03 | B24: =[1]Stress_Scenario!B16 -> OTC derivatives | C24: =[1]Stress_Scenario!C16 -> STU Pension Fund - IR swap | D24: Stressed | E24: =[1]Stress_Scenario!D16 -> 95 | F24: =[1]Stress_Scenario!E16 -> 40 | G24: =[1]Stress_Scenario!F16 -> 0.1 | H24: =[1]Stress_Scenario!G16 -> 0.6 | I24: =[1]Stress_Scenario!H16 -> 59 | J24: =[1]Stress_Scenario!I16 -> 35.4 | K24: =INDEX([1]Portfolio!$J$2:$J$17,MATCH(A24,[1]Portfolio!$A$2:$A$17,0)) -> N
A25: =[1]Stress_Scenario!A17 -> Deriv-04 | B25: =[1]Stress_Scenario!B17 -> OTC derivatives | C25: =[1]Stress_Scenario!C17 -> VWX Sovereign Fund - FX fwd | D25: Stressed | E25: =[1]Stress_Scenario!D17 -> 80 | F25: =[1]Stress_Scenario!E17 -> 45 | G25: =[1]Stress_Scenario!F17 -> 0.1 | H25: =[1]Stress_Scenario!G17 -> 0.3 | I25: =[1]Stress_Scenario!H17 -> 39.5 | J25: =[1]Stress_Scenario!I17 -> 11.85 | K25: =INDEX([1]Portfolio!$J$2:$J$17,MATCH(A25,[1]Portfolio!$A$2:$A$17,0)) -> N
A26: =[1]Stress_Scenario!A18 -> Loan-01 | B26: =[1]Stress_Scenario!B18 -> Loans | C26: =[1]Stress_Scenario!C18 -> YZ Corp | D26: Stressed | E26: =[1]Stress_Scenario!D18 -> 60 | F26: =[1]Stress_Scenario!E18 -> 20 | G26: =[1]Stress_Scenario!F18 -> 0.15 | H26: =[1]Stress_Scenario!G18 -> 1 | I26: =[1]Stress_Scenario!H18 -> 43 | J26: =[1]Stress_Scenario!I18 -> 43 | K26: =INDEX([1]Portfolio!$J$2:$J$17,MATCH(A26,[1]Portfolio!$A$2:$A$17,0)) -> N
A27: =[1]Stress_Scenario!A19 -> Loan-02 | B27: =[1]Stress_Scenario!B19 -> Loans | C27: =[1]Stress_Scenario!C19 -> 12 Corp | D27: Stressed | E27: =[1]Stress_Scenario!D19 -> 45 | F27: =[1]Stress_Scenario!E19 -> 15 | G27: =[1]Stress_Scenario!F19 -> 0.15 | H27: =[1]Stress_Scenario!G19 -> 1 | I27: =[1]Stress_Scenario!H19 -> 32.25 | J27: =[1]Stress_Scenario!I19 -> 32.25 | K27: =INDEX([1]Portfolio!$J$2:$J$17,MATCH(A27,[1]Portfolio!$A$2:$A$17,0)) -> N
A28: =[1]Stress_Scenario!A20 -> Loan-03 | B28: =[1]Stress_Scenario!B20 -> Loans | C28: =[1]Stress_Scenario!C20 -> 34 Real Estate LLC | D28: Stressed | E28: =[1]Stress_Scenario!D20 -> 35 | F28: =[1]Stress_Scenario!E20 -> 10 | G28: =[1]Stress_Scenario!F20 -> 0.15 | H28: =[1]Stress_Scenario!G20 -> 1 | I28: =[1]Stress_Scenario!H20 -> 26.5 | J28: =[1]Stress_Scenario!I20 -> 26.5 | K28: =INDEX([1]Portfolio!$J$2:$J$17,MATCH(A28,[1]Portfolio!$A$2:$A$17,0)) -> N
A29: =[1]Stress_Scenario!A21 -> Sec-01 | B29: =[1]Stress_Scenario!B21 -> Securitization | C29: =[1]Stress_Scenario!C21 -> 56 ABS Tranche | D29: Stressed | E29: =[1]Stress_Scenario!D21 -> 25 | F29: =[1]Stress_Scenario!E21 -> 2.5 | G29: =[1]Stress_Scenario!F21 -> 0.08 | H29: =[1]Stress_Scenario!G21 -> 0.85 | I29: =[1]Stress_Scenario!H21 -> 22.7 | J29: =[1]Stress_Scenario!I21 -> 19.295 | K29: =INDEX([1]Portfolio!$J$2:$J$17,MATCH(A29,[1]Portfolio!$A$2:$A$17,0)) -> Y
... A33: =[1]Stress_Scenario!A25 -> Indem-03 | B33: =[1]Stress_Scenario!B25 -> Indemnified securities financing | C33: =[1]Stress_Scenario!C25 -> 12 Hedge Fund (borrower) | D33: Stressed | E33: =[1]Stress_Scenario!D25 -> 150 | F33: =[1]Stress_Scenario!E25 -> 79 | G33: =[1]Stress_Scenario!F25 -> 0.07 | H33: =[1]Stress_Scenario!G25 -> 0.3 | I33: =[1]Stress_Scenario!H25 -> 76.53 | J33: =[1]Stress_Scenario!I25 -> 22.959 | K33: =INDEX([1]Portfolio!$J$2:$J$17,MATCH(A33,[1]Portfolio!$A$2:$A$17,0)) -> Y
A35: Note: rows 2-17 link to Portfolio (baseline). Rows 18-33 link to Stress_Scenario (Severely Adverse). "Collateral is equity type?" for stressed rows is looked up from Portfolio by matching ID, since Stress_Scenario doesn't repeat that column.

Sheet RWA Summary
A1: RWA Summary: by Category and by Framework
A4: 1. RWA by Category and Scenario
A5: Category | B5: Baseline ($M) | C5: Stressed ($M) | D5: Change ($M) | E5: % of Stressed Total
A6: Indemnified securities financing | B6: =SUMIFS([1]Combined_Data!$J$2:$J$33,[1]Combined_Data!$B$2:$B$33,A6,[1]Combined_Data!$D$2:$D$33,"Baseline") -> 0 | C6: =SUMIFS([1]Combined_Data!$J$2:$J$33,[1]Combined_Data!$B$2:$B$33,A6,[1]Combined_Data!$D$2:$D$33,"Stressed") -> 102.792 | D6: =C6-B6 -> 102.792 | E6: =C6/$C$11 -> 0.26863261
A7: Loans | B7: =SUMIFS([1]Combined_Data!$J$2:$J$33,[1]Combined_Data!$B$2:$B$33,A7,[1]Combined_Data!$D$2:$D$33,"Baseline") -> 99.5 | C7: =SUMIFS([1]Combined_Data!$J$2:$J$33,[1]Combined_Data!$B$2:$B$33,A7,[1]Combined_Data!$D$2:$D$33,"Stressed") -> 101.75 | D7: =C7-B7 -> 2.25 | E7: =C7/$C$11 -> 0.26590949
A8: OTC derivatives | B8: =SUMIFS([1]Combined_Data!$J$2:$J$33,[1]Combined_Data!$B$2:$B$33,A8,[1]Combined_Data!$D$2:$D$33,"Baseline") -> 99.95 | C8: =SUMIFS([1]Combined_Data!$J$2:$J$33,[1]Combined_Data!$B$2:$B$33,A8,[1]Combined_Data!$D$2:$D$33,"Stressed") -> 128.85 | D8: =C8-B8 -> 28.9 | E8: =C8/$C$11 -> 0.33673157
A9: Repo-style transactions | B9: =SUMIFS([1]Combined_Data!$J$2:$J$33,[1]Combined_Data!$B$2:$B$33,A9,[1]Combined_Data!$D$2:$D$33,"Baseline") -> 0 | C9: =SUMIFS([1]Combined_Data!$J$2:$J$33,[1]Combined_Data!$B$2:$B$33,A9,[1]Combined_Data!$D$2:$D$33,"Stressed") -> 14.526 | D9: =C9-B9 -> 14.526 | E9: =C9/$C$11 -> 0.037961683
A10: Securitization | B10: =SUMIFS([1]Combined_Data!$J$2:$J$33,[1]Combined_Data!$B$2:$B$33,A10,[1]Combined_Data!$D$2:$D$33,"Baseline") -> 27.2025 | C10: =SUMIFS([1]Combined_Data!$J$2:$J$33,[1]Combined_Data!$B$2:$B$33,A10,[1]Combined_Data!$D$2:$D$33,"Stressed") -> 34.731 | D10: =C10-B10 -> 7.5285 | E10: =C10/$C$11 -> 0.090764643
A11: Grand Total | B11: =SUM(B6:B10) -> 226.6525 | C11: =SUM(C6:C10) -> 382.649 | D11: =SUM(D6:D10) -> 155.9965 | E11: =C11/C11 -> 1
A14: 2. Framework Bridge (Stressed), reconciled to Basel_III_Endgame
A15: Line item | B15: 2023 draft ($M) | C15: 2026 re-proposal ($M)
A16: Current Basel III RWA, Stressed (from Section 1) | B16: =$C$11 -> 382.649 | C16: =$C$11 -> 382.649
A17: + CVA RWA add-on (Derivatives only, stressed) | B17: =[1]Basel_III_Endgame!$B$26 -> 25.77 | C17: =[1]Basel_III_Endgame!$B$26 -> 25.77
A18: + Operational Risk RWA (firm-wide, not tied to any category) | B18: =[1]Basel_III_Endgame!$B$21 -> 58.5 | C18: =[1]Basel_III_Endgame!$B$22 -> 22.5
A19: Endgame Stressed RWA (computed here) | B19: =B16+B17+B18 -> 466.919 | C19: =C16+C17+C18 -> 430.919
A20: Basel_III_Endgame tab shows (for comparison) | B20: =[1]Basel_III_Endgame!$C$31 -> 466.919 | C20: =[1]Basel_III_Endgame!$C$32 -> 430.919
A21: Check: difference (should be $0.0) | B21: =B19-B20 -> 0 | C21: =C19-C20 -> 0
A25: 3. Current Basel III vs. Endgame, Stressed (Severely Adverse)
A26: Framework | B26: Stressed RWA ($M) | C26: Change vs. Current ($M) | D26: Stressed CET1 Ratio | E26: Buffer above 4.5% floor
A27: Current Basel III | B27: =[1]Basel_III_Endgame!$C$30 -> 382.649 | C27: =B27-$B$27 -> 0 | D27: =[1]Basel_III_Endgame!$D$37 -> 0.057493944 | E27: =D27-0.045 -> 0.012493944
A28: Endgame, 2023 draft | B28: =[1]Basel_III_Endgame!$C$31 -> 466.919 | C28: =B28-$B$27 -> 84.27 | D28: =[1]Basel_III_Endgame!$D$39 -> 0.04711738 | E28: =D28-0.045 -> 0.0021173801
A29: Endgame, 2026 re-proposal | B29: =[1]Basel_III_Endgame!$C$32 -> 430.919 | C29: =B29-$B$27 -> 48.27 | D29: =[1]Basel_III_Endgame!$D$41 -> 0.051053678 | E29: =D29-0.045 -> 0.0060536783
A31: Note: 'Buffer above 4.5% floor' highlights red when under 1.0 percentage point, since that is the zone examiners and rating agencies watch most closely. The 2023 draft sits at only 0.2 points above the floor; the 2026 re-proposal restores about 0.4 points of that buffer, entirely from the fee-income netting change, not from any change to the underlying portfolio.
